[
    { "label": "English", "value": "en" },
    { "label": "Spanish", "value": "es" },
    { "label": "French", "value": "fr" },
    { "label": "German", "value": "de" },
    { "label": "Chinese (Simplified)", "value": "zh-CN" },
    { "label": "Chinese (Traditional)", "value": "zh-TW" },
    { "label": "Japanese", "value": "ja" },
    { "label": "Korean", "value": "ko" },
    { "label": "Arabic", "value": "ar" },
    { "label": "Portuguese", "value": "pt" },
    { "label": "Russian", "value": "ru" },
    { "label": "Italian", "value": "it" },
    { "label": "Dutch", "value": "nl" },
    { "label": "Turkish", "value": "tr" },
    { "label": "Polish", "value": "pl" },
    { "label": "Swedish", "value": "sv" },
    { "label": "Danish", "value": "da" },
    { "label": "Finnish", "value": "fi" },
    { "label": "Norwegian", "value": "no" },
    { "label": "Greek", "value": "el" },
    { "label": "Hindi", "value": "hi" },
    { "label": "Thai", "value": "th" },
    { "label": "Vietnamese", "value": "vi" },
    { "label": "Hebrew", "value": "he" },
    { "label": "Persian", "value": "fa" },
    { "label": "Indonesian", "value": "id" },
    { "label": "Malay", "value": "ms" },
    { "label": "Czech", "value": "cs" },
    { "label": "Hungarian", "value": "hu" },
    { "label": "Romanian", "value": "ro" },
    { "label": "Slovak", "value": "sk" },
    { "label": "Ukrainian", "value": "uk" },
    { "label": "Bulgarian", "value": "bg" },
    { "label": "Croatian", "value": "hr" },
    { "label": "Serbian", "value": "sr" },
    { "label": "Estonian", "value": "et" },
    { "label": "Latvian", "value": "lv" },
    { "label": "Lithuanian", "value": "lt" },
    { "label": "Slovenian", "value": "sl" },
    { "label": "Macedonian", "value": "mk" },
    { "label": "Albanian", "value": "sq" },
    { "label": "Swahili", "value": "sw" },
    { "label": "Tagalog", "value": "tl" },
    { "label": "Afrikaans", "value": "af" },
    { "label": "Bengali", "value": "bn" },
    { "label": "Tamil", "value": "ta" },
    { "label": "Telugu", "value": "te" },
    { "label": "Malayalam", "value": "ml" },
    { "label": "Punjabi", "value": "pa" },
    { "label": "Gujarati", "value": "gu" },
    { "label": "Marathi", "value": "mr" },
    { "label": "Kannada", "value": "kn" },
    { "label": "Urdu", "value": "ur" }
]
